{
  "language": "de",
  "title": "Brokkoli-Auflauf",
  "default_servings": 2,
  "serving_unit": "Portionen",
  "meal_type": "main",
  "tags": [
    "vegetarian"
  ],
  "serve_with": [
    "salted_potatoes"
  ],
  "version": 1,
  "ingredients": [
    {
      "name": "frischer Brokkoli (mit Stiel)",
      "amount": 1,
      "unit": "kg"
    },
    {
      "name": "Sauce Hollandaise",
      "amount": 1,
      "unit": "package"
    },
    {
      "name": "Streukäse",
      "amount": 200,
      "unit": "g"
    }
  ],
  "instructions": [
    "Die Sauce Hollandaise in der Mikrowelle erhitzen und in eine Auflaufform geben.",
    "Den Brokkoli kochen und in die Auflaufform geben.",
    "Mit Streukäse bestreuen.",
    "Bei {{!180 °C}} backen."
  ],
  "translations": {
    "en": {
      "title": "Broccoli Bake",
      "serving_unit": "servings",
      "ingredients": [
        "fresh broccoli (with stalk)",
        "sauce hollandaise",
        "grated cheese"
      ],
      "instructions": [
        "Heat the sauce hollandaise in the microwave and pour into a baking dish.",
        "Cook the broccoli and add it to the baking dish.",
        "Sprinkle with grated cheese.",
        "Bake at {{!180 °C}}."
      ]
    }
  }
}